macro_flow-0.0.4.dist-info/licenses/LICENCE
macro_flow_chunks/__init__.py
macro_flow_chunks/main.py
macro_flow_chunks/contracts/__init__.py
macro_flow_chunks/contracts/contractsETL.py
macro_flow_chunks/extract/__init__.py
macro_flow_chunks/extract/extract.py
macro_flow_chunks/load/__init__.py
macro_flow_chunks/load/load.py
macro_flow_chunks/transform/__init__.py
macro_flow_chunks/transform/transform.py
macro_flow-0.0.4.dist-info/METADATA
macro_flow-0.0.4.dist-info/WHEEL
macro_flow-0.0.4.dist-info/entry_points.txt
macro_flow-0.0.4.dist-info/top_level.txt
macro_flow-0.0.4.dist-info/RECORD
