Metadata-Version: 2.4
Name: macro-flow
Version: 0.0.4
Summary: ETL Para banco macro, extrae pdf desde la url que le pongas, extrae datos y crea chunks que sube a s3 (aws)
Home-page: https://github.com/facuvegaingenieer/macro-flow
Author: Walter Facundo Vega
Author-email: facundo.vega1234@gmail.com
License: MIT
Classifier: Programming Language :: Python :: 3
Classifier: Programming Language :: Python :: 3.8
Classifier: License :: OSI Approved :: MIT License
Classifier: Operating System :: OS Independent
Requires-Python: >=3.8
License-File: LICENCE
Requires-Dist: pandas
Requires-Dist: boto3
Requires-Dist: pyarrow
Requires-Dist: python-dotenv
Requires-Dist: requests
Requires-Dist: pdfplumber
Requires-Dist: langchain
Dynamic: author
Dynamic: author-email
Dynamic: classifier
Dynamic: description
Dynamic: description-content-type
Dynamic: home-page
Dynamic: license
Dynamic: license-file
Dynamic: requires-dist
Dynamic: requires-python
Dynamic: summary
